LICENSE.md
MANIFEST.in
README.md
setup.cfg
setup.py
django_pluggableappsettings/__init__.py
django_pluggableappsettings.egg-info/PKG-INFO
django_pluggableappsettings.egg-info/SOURCES.txt
django_pluggableappsettings.egg-info/dependency_links.txt
django_pluggableappsettings.egg-info/pbr.json
django_pluggableappsettings.egg-info/requires.txt
django_pluggableappsettings.egg-info/top_level.txt
django_pluggableappsettings/test/__init__.py
django_pluggableappsettings/test/utils.py
django_pluggableappsettings/tests/test/__init__.py
django_pluggableappsettings/tests/test/test_utils.py